ascii_chiper/__init__.py
ascii_chiper/chiper.py
ascii_chiper/exceptions.py
ascii_chiper/helpers.py
ascii_chiper/key_generator.py
ascii_chiper/models.py
ascii_chiper/utils.py
ascii_chiper-0.2.0.dist-info/licenses/LICENSE
ascii_chiper-0.2.0.dist-info/METADATA
ascii_chiper-0.2.0.dist-info/WHEEL
ascii_chiper-0.2.0.dist-info/top_level.txt
ascii_chiper-0.2.0.dist-info/RECORD
