Metadata-Version: 2.4
Name: ascii_chiper
Version: 0.2.0
Summary: A versatile Python module for encrypting and decrypting strings, integers, and dictionaries using a variety of encryption techniques.
Home-page: https://github.com/glizzykingdreko/ascii_chiper
Author: glizzykingdreko
Author-email: glizzykingdreko@protonmail.com
Classifier: Development Status :: 3 - Alpha
Classifier: Intended Audience :: Developers
Classifier: License :: OSI Approved :: MIT License
Classifier: Operating System :: OS Independent
Classifier: Programming Language :: Python :: 3
Classifier: Programming Language :: Python :: 3.6
Classifier: Programming Language :: Python :: 3.7
Classifier: Programming Language :: Python :: 3.8
Classifier: Programming Language :: Python :: 3.9
Requires-Python: >=3.6
License-File: LICENSE
Requires-Dist: numpy
Dynamic: author
Dynamic: author-email
Dynamic: classifier
Dynamic: description
Dynamic: description-content-type
Dynamic: home-page
Dynamic: license-file
Dynamic: requires-dist
Dynamic: requires-python
Dynamic: summary
